systemeval/__init__.py
systemeval/cli_helpers.py
systemeval/cli_main.py
systemeval/config.py
systemeval/e2e_config.py
systemeval/e2e_types.py
systemeval/adapters/__init__.py
systemeval/adapters/base.py
systemeval/adapters/registry.py
systemeval/adapters/repositories.py
systemeval/adapters/browser/__init__.py
systemeval/adapters/browser/playwright_adapter.py
systemeval/adapters/js/__init__.py
systemeval/adapters/js/base.py
systemeval/adapters/js/jest_adapter.py
systemeval/adapters/js/vitest_adapter.py
systemeval/adapters/python/__init__.py
systemeval/adapters/python/pytest_adapter.py
systemeval/adapters/python/pipeline/__init__.py
systemeval/adapters/python/pipeline/adapter.py
systemeval/cli/__init__.py
systemeval/cli/commands/__init__.py
systemeval/cli/commands/config_commands.py
systemeval/cli/commands/docker_commands.py
systemeval/cli/commands/e2e_commands.py
systemeval/cli/commands/list_commands.py
systemeval/cli/commands/test_commands.py
systemeval/cli/execution/__init__.py
systemeval/cli/execution/multiproject.py
systemeval/cli/formatters/__init__.py
systemeval/cli/formatters/base.py
systemeval/cli/formatters/console_formatter.py
systemeval/cli/formatters/json_formatter.py
systemeval/cli/formatters/template_formatter.py
systemeval/cli/formatting/__init__.py
systemeval/cli/formatting/results.py
systemeval/config/__init__.py
systemeval/config/adapters.py
systemeval/config/core.py
systemeval/config/e2e.py
systemeval/config/environments.py
systemeval/config/loaders.py
systemeval/config/multiproject.py
systemeval/core/__init__.py
systemeval/core/criteria.py
systemeval/core/evaluation.py
systemeval/core/reporter.py
systemeval/e2e/__init__.py
systemeval/e2e/examples.py
systemeval/e2e/factory.py
systemeval/e2e/git_analyzer.py
systemeval/e2e/protocols.py
systemeval/e2e/registry.py
systemeval/e2e/types.py
systemeval/e2e/analysis/__init__.py
systemeval/e2e/analysis/git_analyzer.py
systemeval/e2e/core/__init__.py
systemeval/e2e/core/protocols.py
systemeval-0.7.1.dist-info/licenses/LICENSE
systemeval-0.7.1.dist-info/METADATA
systemeval-0.7.1.dist-info/WHEEL
systemeval-0.7.1.dist-info/entry_points.txt
systemeval-0.7.1.dist-info/top_level.txt
systemeval-0.7.1.dist-info/RECORD
