Metadata-Version: 2.4
Name: systemeval
Version: 0.7.1
Summary: AI-powered test orchestration platform: traditional testing (pytest, jest, playwright) + DebuggAI natural language tests, commit-based generation, and visual failure analysis
Author-email: DebuggAI <dev@debugg.ai>
License: MIT
Project-URL: Homepage, https://debugg.ai
Project-URL: Documentation, https://debugg.ai/docs/systemeval
Project-URL: Repository, https://github.com/debugg-ai/systemeval
Project-URL: Issues, https://github.com/debugg-ai/systemeval/issues
Project-URL: Changelog, https://github.com/debugg-ai/systemeval/blob/main/CHANGES.md
Keywords: testing,pytest,jest,cli,test-runner,pipeline,e2e
Classifier: Development Status :: 3 - Alpha
Classifier: Environment :: Console
Classifier: Intended Audience :: Developers
Classifier: License :: OSI Approved :: MIT License
Classifier: Programming Language :: Python :: 3
Classifier: Programming Language :: Python :: 3.9
Classifier: Programming Language :: Python :: 3.10
Classifier: Programming Language :: Python :: 3.11
Classifier: Programming Language :: Python :: 3.12
Classifier: Topic :: Software Development :: Testing
Requires-Python: >=3.9
License-File: LICENSE
Requires-Dist: click>=8.0
Requires-Dist: pyyaml>=6.0
Requires-Dist: rich>=13.0
Requires-Dist: pydantic>=2.0
Requires-Dist: jinja2>=3.0
Provides-Extra: pytest
Requires-Dist: pytest>=7.0; extra == "pytest"
Requires-Dist: pytest-cov>=4.0; extra == "pytest"
Requires-Dist: pytest-xdist>=3.0; extra == "pytest"
Provides-Extra: jest
Provides-Extra: django
Requires-Dist: Django>=4.0; extra == "django"
Provides-Extra: pipeline
Requires-Dist: systemeval[django]; extra == "pipeline"
Provides-Extra: dev
Requires-Dist: systemeval[pytest]; extra == "dev"
Requires-Dist: black; extra == "dev"
Requires-Dist: ruff; extra == "dev"
Requires-Dist: mypy; extra == "dev"
Dynamic: license-file
